[{"cod_telf_user":"70000","cod_rol, cod_grupo, cod_usuario":"0,0,1"},{"cod_telf_user":70001,"cod_rol, cod_grupo, cod_usuario":"1,1,2"},{"cod_telf_user":70002,"cod_rol, cod_grupo, cod_usuario":"2,2,3"},{"cod_telf_user":70003,"cod_rol, cod_grupo, cod_usuario":"3,3,4"},{"cod_telf_user":70004,"cod_rol, cod_grupo, cod_usuario":"4,4,5"},{"cod_telf_user":70005,"cod_rol, cod_grupo, cod_usuario":"0,5,6"},{"cod_telf_user":70006,"cod_rol, cod_grupo, cod_usuario":"1,6,7"},{"cod_telf_user":70007,"cod_rol, cod_grupo, cod_usuario":"2,7,8"},{"cod_telf_user":70008,"cod_rol, cod_grupo, cod_usuario":"3,8,9"},{"cod_telf_user":70009,"cod_rol, cod_grupo, cod_usuario":"4,9,10"}]