[{"tablename":"rol","nivel":0},{"tablename":"grupo","nivel":0},{"tablename":"tipo_evaluacion","nivel":0},{"tablename":"gestion","nivel":0},{"tablename":"tipo_documento","nivel":0},{"tablename":"usuario","nivel":1},{"tablename":"horario","nivel":1},{"tablename":"convocatoria","nivel":1},{"tablename":"telefono_user","nivel":2},{"tablename":"foro","nivel":2},{"tablename":"email_user","nivel":2},{"tablename":"chat","nivel":2},{"tablename":"hora_presentacion","nivel":2},{"tablename":"grupo_empresa","nivel":2},{"tablename":"documento","nivel":2},{"tablename":"configuracion_semestral","nivel":2},{"tablename":"integrantes","nivel":3},{"tablename":"contrato_empresa","nivel":3},{"tablename":"archivos_empresa","nivel":3},{"tablename":"configuracion","nivel":3},{"tablename":"telefono_integrante","nivel":4},{"tablename":"reunion_evaluativo","nivel":4},{"tablename":"email_integrante","nivel":4},{"tablename":"evaluacion_archivos","nivel":4}]