[{"periodo":"1","año":"1970","activo":"true","nombre":"RECURSOS NATURALES","id_materia":"1"},{"periodo":2,"año":1971,"activo":"true","nombre":"\r\nLABORATORIO DE QUIMICA GENERAL","id_materia":2},{"periodo":3,"año":1972,"activo":"true","nombre":"\r\nQUIMICA GENERAL","id_materia":3},{"periodo":4,"año":1973,"activo":"true","nombre":"\r\nFISICA BASICA I","id_materia":4},{"periodo":"1","año":1974,"activo":"true","nombre":"\r\nCALCULO I","id_materia":5},{"periodo":2,"año":1975,"activo":"true","nombre":"\r\nLINEAL Y TEORIA MATRICIAL","id_materia":6},{"periodo":3,"año":1976,"activo":"true","nombre":"\r\nEQUILIBRIOS EN DISOLUCION","id_materia":7},{"periodo":4,"año":1977,"activo":"true","nombre":"\r\nQUIMICA INORGANICA","id_materia":8},{"periodo":"1","año":1978,"activo":"true","nombre":"\r\nLABORATORIO DE QUIMICA ANALITICA","id_materia":9},{"periodo":2,"año":1979,"activo":"true","nombre":"\r\nFISICA BASICA II","id_materia":10},{"periodo":3,"año":1980,"activo":"true","nombre":"\r\nCALCULO II","id_materia":11},{"periodo":4,"año":1981,"activo":"true","nombre":"\r\nESTADISTICA APLICADA","id_materia":12},{"periodo":"1","año":1982,"activo":"true","nombre":"\r\nBIOLOGIA CELULAR","id_materia":13},{"periodo":2,"año":1983,"activo":"true","nombre":"\r\nFISICOQUIMICA","id_materia":14},{"periodo":3,"año":1984,"activo":"true","nombre":"\r\nLABORATORIO DE FISICOQUIMICA","id_materia":15},{"periodo":4,"año":1985,"activo":"true","nombre":"\r\nFISICA BASICA III","id_materia":16},{"periodo":"1","año":1986,"activo":"true","nombre":"\r\nCALCULO III","id_materia":17},{"periodo":2,"año":1987,"activo":"true","nombre":"\r\nANALISIS NUMERICO","id_materia":18},{"periodo":3,"año":1988,"activo":"true","nombre":"\r\nLABORATORIO DE QUIMICA ORGANICA","id_materia":19},{"periodo":4,"año":1989,"activo":"true","nombre":"\r\nQUIMICA ORGANICA","id_materia":20},{"periodo":"1","año":1990,"activo":"true","nombre":"\r\nINTRODUCCION A LOS PROCESOS QUIMICOS","id_materia":21},{"periodo":2,"año":1991,"activo":"true","nombre":"\r\nTERMODINAMICA GENERAL","id_materia":22},{"periodo":3,"año":1992,"activo":"true","nombre":"\r\nECONOMIA Y ADMINISTRACION INDUSTRIAL","id_materia":23},{"periodo":4,"año":1993,"activo":"true","nombre":"\r\nDIBUJO TECNICO","id_materia":24},{"periodo":"1","año":1994,"activo":"true","nombre":"\r\nQUIMICA ORGANICA II","id_materia":25},{"periodo":2,"año":1995,"activo":"true","nombre":"\r\nQUIMICA BIOLOGICA","id_materia":26},{"periodo":3,"año":1996,"activo":"true","nombre":"\r\nLABORATORIO DE QUIMICA ORGANICA II","id_materia":27},{"periodo":4,"año":1997,"activo":"true","nombre":"\r\nLABORATORIO DE QUIMICA ANALITICA","id_materia":28},{"periodo":"1","año":1998,"activo":"true","nombre":"\r\nFENOMENOS DE TRANSPORTE GENERAL","id_materia":29},{"periodo":2,"año":1999,"activo":"true","nombre":"\r\nINGENIERIA DE ALIMENTOS I","id_materia":30},{"periodo":3,"año":2000,"activo":"true","nombre":"\r\nANALISIS INSTRUMENTAL","id_materia":31},{"periodo":4,"año":2001,"activo":"true","nombre":"\r\nQUIMICA DE ALIMENTOS","id_materia":32},{"periodo":"1","año":2002,"activo":"true","nombre":"\r\nINTRODUCCION A LA INGENIERIA BIOQUIMICA","id_materia":33},{"periodo":2,"año":2003,"activo":"true","nombre":"\r\nMICROBIOLOGIA DE LOS ALIMENTOS","id_materia":34},{"periodo":3,"año":2004,"activo":"true","nombre":"\r\nCOSTOS INDUSTRIALES","id_materia":35},{"periodo":4,"año":2005,"activo":"true","nombre":"\r\nINGENIERIA DE ALIMENTOS II","id_materia":36},{"periodo":"1","año":2006,"activo":"true","nombre":"\r\nLABORATORIO DE ANALISIS DE ALIMENTOS","id_materia":37},{"periodo":2,"año":2007,"activo":"true","nombre":"\r\nNUTRICION","id_materia":38},{"periodo":3,"año":2008,"activo":"true","nombre":"\r\nINDUSTRIA DE LOS CEREALES","id_materia":39},{"periodo":4,"año":2009,"activo":"true","nombre":"\r\nINGENIERIA DE ALIMENTOS III","id_materia":40},{"periodo":"1","año":"1970","activo":"true","nombre":"\r\nINTRODUCCION A LA INGENIERIA MEDIO","id_materia":41},{"periodo":2,"año":1971,"activo":"true","nombre":"\r\nINDUSTRIAS DE GRASAS Y ACEITES","id_materia":42},{"periodo":3,"año":1972,"activo":"true","nombre":"\r\nINDUSTRIA DE FRUTAS Y HORTALIZAS","id_materia":43},{"periodo":4,"año":1973,"activo":"true","nombre":"\r\nINDUSTRIA DE BEBIDAS","id_materia":44},{"periodo":"1","año":1974,"activo":"true","nombre":"\r\nSISTEMAS DE CALIDAD EN ALIMENTOS","id_materia":45},{"periodo":2,"año":1975,"activo":"true","nombre":"\r\nDISENO DE PLANTAS AGRO-ALIMENTARIAS","id_materia":46},{"periodo":3,"año":1976,"activo":"true","nombre":"\r\nDISENO EXPERIMENTAL","id_materia":47},{"periodo":4,"año":1977,"activo":"true","nombre":"\r\nINDUSTRIAS CARNICAS","id_materia":48},{"periodo":"1","año":1978,"activo":"true","nombre":"\r\nTECNOLOGIA DEL FRIO","id_materia":49},{"periodo":2,"año":1979,"activo":"true","nombre":"\r\nINGLES","id_materia":50}]